{
    "time_checker": {
        "checker": "time_checker",
        "question": "time_checker",
        "sample_mean": 0.9664371772805508,
        "sample_variance": 0.0324145657082635,
        "total": 1162.0,
        "positives": 1123.0,
        "squared_diffs_sum": 37.63331078729393
    },
    "current_round": {
        "checker": "time_checker",
        "question": "Which is the current round of the game?",
        "sample_mean": 1.0,
        "sample_variance": 0.0,
        "total": 70.0,
        "positives": 70.0,
        "squared_diffs_sum": 0.0
    },
    "action_A": {
        "checker": "time_checker",
        "question": "Which action did player A play in round {}?",
        "sample_mean": 1.0,
        "sample_variance": 0.0,
        "total": 273.0,
        "positives": 273.0,
        "squared_diffs_sum": 0.0
    },
    "action_B": {
        "checker": "time_checker",
        "question": "Which action did player B play in round {}?",
        "sample_mean": 0.9706959706959707,
        "sample_variance": 0.028313583910920308,
        "total": 273.0,
        "positives": 265.0,
        "squared_diffs_sum": 7.701294823770324
    },
    "points_A": {
        "checker": "time_checker",
        "question": "How many points did player A collect in round {}?",
        "sample_mean": 0.9487179487179487,
        "sample_variance": 0.04847854429315089,
        "total": 273.0,
        "positives": 259.0,
        "squared_diffs_sum": 13.186164047737043
    },
    "points_B": {
        "checker": "time_checker",
        "question": "How many points did player B collect in round {}?",
        "sample_mean": 0.9377289377289377,
        "sample_variance": 0.05827639121188007,
        "total": 273.0,
        "positives": 256.0,
        "squared_diffs_sum": 15.85117840963138
    }
}